swift/__init__.py
swift/version.py
swift/cli/__init__.py
swift/cli/app.py
swift/cli/deploy.py
swift/cli/eval.py
swift/cli/export.py
swift/cli/infer.py
swift/cli/main.py
swift/cli/merge_lora.py
swift/cli/pt.py
swift/cli/rlhf.py
swift/cli/rollout.py
swift/cli/sample.py
swift/cli/sft.py
swift/cli/utils.py
swift/cli/web_ui.py
swift/cli/_megatron/__init__.py
swift/cli/_megatron/export.py
swift/cli/_megatron/main.py
swift/cli/_megatron/pt.py
swift/cli/_megatron/rlhf.py
swift/cli/_megatron/sft.py
swift/hub/__init__.py
swift/hub/constant.py
swift/hub/hub.py
swift/llm/__init__.py
swift/llm/base.py
swift/llm/data_loader.py
swift/llm/utils.py
swift/llm/app/__init__.py
swift/llm/app/app.py
swift/llm/app/build_ui.py
swift/llm/app/locale.py
swift/llm/argument/__init__.py
swift/llm/argument/app_args.py
swift/llm/argument/deploy_args.py
swift/llm/argument/eval_args.py
swift/llm/argument/export_args.py
swift/llm/argument/infer_args.py
swift/llm/argument/merge_args.py
swift/llm/argument/rlhf_args.py
swift/llm/argument/sampling_args.py
swift/llm/argument/train_args.py
swift/llm/argument/tuner_args.py
swift/llm/argument/webui_args.py
swift/llm/argument/base_args/__init__.py
swift/llm/argument/base_args/base_args.py
swift/llm/argument/base_args/data_args.py
swift/llm/argument/base_args/generation_args.py
swift/llm/argument/base_args/model_args.py
swift/llm/argument/base_args/quant_args.py
swift/llm/argument/base_args/ray_args.py
swift/llm/argument/base_args/template_args.py
swift/llm/argument/base_args/utils.py
swift/llm/dataset/__init__.py
swift/llm/dataset/indexed_dataset.py
swift/llm/dataset/loader.py
swift/llm/dataset/media.py
swift/llm/dataset/register.py
swift/llm/dataset/utils.py
swift/llm/dataset/data/dataset_info.json
swift/llm/dataset/dataset/__init__.py
swift/llm/dataset/dataset/llm.py
swift/llm/dataset/dataset/mllm.py
swift/llm/dataset/preprocessor/__init__.py
swift/llm/dataset/preprocessor/core.py
swift/llm/dataset/preprocessor/extra.py
swift/llm/ds_config/zero0.json
ms_swift-3.12.3.dist-info/LICENSE
ms_swift-3.12.3.dist-info/METADATA
ms_swift-3.12.3.dist-info/WHEEL
ms_swift-3.12.3.dist-info/entry_points.txt
ms_swift-3.12.3.dist-info/top_level.txt
ms_swift-3.12.3.dist-info/RECORD
