Metadata-Version: 2.1
Name: ms_swift
Version: 3.12.3
Summary: Swift: Scalable lightWeight Infrastructure for Fine-Tuning
Home-page: https://github.com/modelscope/ms-swift
Author: DAMO ModelScope teams
Author-email: contact@modelscope.cn
License: Apache License 2.0
Keywords: transformers,LLM,lora,megatron,grpo,sft
Classifier: Development Status :: 4 - Beta
Classifier: License :: OSI Approved :: Apache Software License
Classifier: Operating System :: OS Independent
Classifier: Programming Language :: Python :: 3
Classifier: Programming Language :: Python :: 3.8
Classifier: Programming Language :: Python :: 3.9
Classifier: Programming Language :: Python :: 3.10
Classifier: Programming Language :: Python :: 3.11
Classifier: Programming Language :: Python :: 3.12
Requires-Python: >=3.8.0
License-File: LICENSE
Requires-Dist: accelerate
Requires-Dist: addict
Requires-Dist: aiohttp
Requires-Dist: attrdict
Requires-Dist: binpacking
Requires-Dist: charset-normalizer
Requires-Dist: cpm-kernels
Requires-Dist: dacite
Requires-Dist: datasets<4.0,>=3.0
Requires-Dist: einops
Requires-Dist: fastapi
Requires-Dist: gradio<6.0,>=3.40.0
Requires-Dist: importlib-metadata
Requires-Dist: jieba
Requires-Dist: json-repair
Requires-Dist: matplotlib
Requires-Dist: modelscope>=1.23
Requires-Dist: nltk
Requires-Dist: numpy
Requires-Dist: omegaconf
Requires-Dist: openai
Requires-Dist: oss2
Requires-Dist: pandas
Requires-Dist: peft<0.19,>=0.11
Requires-Dist: pillow
Requires-Dist: PyYAML>=5.4
Requires-Dist: requests
Requires-Dist: rouge
Requires-Dist: safetensors
Requires-Dist: scipy
Requires-Dist: sentencepiece
Requires-Dist: simplejson>=3.3.0
Requires-Dist: sortedcontainers>=1.5.9
Requires-Dist: tensorboard
Requires-Dist: tiktoken
Requires-Dist: tqdm
Requires-Dist: transformers<4.58,>=4.33
Requires-Dist: transformers-stream-generator
Requires-Dist: trl<0.25,>=0.15
Requires-Dist: uvicorn
Requires-Dist: zstandard
Provides-Extra: all
Requires-Dist: accelerate; extra == "all"
Requires-Dist: addict; extra == "all"
Requires-Dist: aiohttp; extra == "all"
Requires-Dist: attrdict; extra == "all"
Requires-Dist: binpacking; extra == "all"
Requires-Dist: charset-normalizer; extra == "all"
Requires-Dist: cpm-kernels; extra == "all"
Requires-Dist: dacite; extra == "all"
Requires-Dist: datasets<4.0,>=3.0; extra == "all"
Requires-Dist: einops; extra == "all"
Requires-Dist: fastapi; extra == "all"
Requires-Dist: gradio<6.0,>=3.40.0; extra == "all"
Requires-Dist: importlib-metadata; extra == "all"
Requires-Dist: jieba; extra == "all"
Requires-Dist: json-repair; extra == "all"
Requires-Dist: matplotlib; extra == "all"
Requires-Dist: modelscope>=1.23; extra == "all"
Requires-Dist: nltk; extra == "all"
Requires-Dist: numpy; extra == "all"
Requires-Dist: omegaconf; extra == "all"
Requires-Dist: openai; extra == "all"
Requires-Dist: oss2; extra == "all"
Requires-Dist: pandas; extra == "all"
Requires-Dist: peft<0.19,>=0.11; extra == "all"
Requires-Dist: pillow; extra == "all"
Requires-Dist: PyYAML>=5.4; extra == "all"
Requires-Dist: requests; extra == "all"
Requires-Dist: rouge; extra == "all"
Requires-Dist: safetensors; extra == "all"
Requires-Dist: scipy; extra == "all"
Requires-Dist: sentencepiece; extra == "all"
Requires-Dist: simplejson>=3.3.0; extra == "all"
Requires-Dist: sortedcontainers>=1.5.9; extra == "all"
Requires-Dist: tensorboard; extra == "all"
Requires-Dist: tiktoken; extra == "all"
Requires-Dist: tqdm; extra == "all"
Requires-Dist: transformers<4.58,>=4.33; extra == "all"
Requires-Dist: transformers-stream-generator; extra == "all"
Requires-Dist: trl<0.25,>=0.15; extra == "all"
Requires-Dist: uvicorn; extra == "all"
Requires-Dist: zstandard; extra == "all"
Requires-Dist: evalscope>=1.0.0; extra == "all"
Requires-Dist: evalscope[opencompass]; extra == "all"
Requires-Dist: evalscope[vlmeval]; extra == "all"
Requires-Dist: swanlab; extra == "all"
Requires-Dist: ray; extra == "all"
Provides-Extra: eval
Requires-Dist: evalscope>=1.0.0; extra == "eval"
Requires-Dist: evalscope[opencompass]; extra == "eval"
Requires-Dist: evalscope[vlmeval]; extra == "eval"
Provides-Extra: ray
Requires-Dist: ray; extra == "ray"
Provides-Extra: swanlab
Requires-Dist: swanlab; extra == "swanlab"
